{"version":2,"kind":"Article","sha256":"d3332c1ac741329660fd9f643f49f3d8597e651f0d719295a678424085336bf4","slug":"slides.slides05","location":"/slides/slides05.md","dependencies":[],"frontmatter":{"title":"Automated Documentation","content_includes_title":false,"authors":[{"id":"LH","nameParsed":{"literal":"Luca Heltai","given":"Luca","family":"Heltai"},"name":"Luca Heltai","orcid":"0000-0001-5514-4683","email":"luca.heltai@unipi.it","affiliations":["unipi"],"github":"luca-heltai","linkedin":"https://www.linkedin.com/in/heltai/","youtube":"UCK0glvtKYmVPJbpurdlt9pw","corresponding":true}],"github":"https://github.com/luca-heltai/sspa","copyright":"2025","affiliations":[{"id":"unipi","name":"University of Pisa","department":"Department of Mathematics","address":"Largo Bruno Pontecorvo 5, 56127 Pisa, Italy","city":"Pisa","postal_code":"56127","country":"Italy","ror":"https://ror.org/03ad39j10","phone":"+39 050 221 3824"}],"numbering":{"title":{"offset":1}},"source_url":"https://github.com/luca-heltai/sspa/blob/main/jupyterbook/slides/slides05.md","edit_url":"https://github.com/luca-heltai/sspa/edit/main/jupyterbook/slides/slides05.md","exports":[{"format":"md","filename":"slides05.md","url":"/sspa//build/slides05-3148e603266a91e2900ca1161fc532ab.md"}]},"mdast":{"type":"root","children":[{"type":"block","children":[{"type":"thematicBreak","position":{"start":{"line":3,"column":1},"end":{"line":3,"column":1}},"key":"MK7UN8yqx7"},{"type":"heading","depth":2,"position":{"start":{"line":5,"column":1},"end":{"line":5,"column":1}},"children":[{"type":"text","value":"Why automate docs","position":{"start":{"line":5,"column":1},"end":{"line":5,"column":1}},"key":"tJI9T0rhYo"}],"identifier":"why-automate-docs","label":"Why automate docs","html_id":"why-automate-docs","implicit":true,"key":"FDWYQKmraM"},{"type":"list","ordered":false,"spread":false,"position":{"start":{"line":7,"column":1},"end":{"line":11,"column":1}},"children":[{"type":"listItem","spread":true,"position":{"start":{"line":7,"column":1},"end":{"line":7,"column":1}},"children":[{"type":"paragraph","children":[{"type":"text","value":"Keep API reference and tutorials in sync with code; avoid stale README snippets.","position":{"start":{"line":7,"column":1},"end":{"line":7,"column":1}},"key":"QsmIOIXeFv"}],"key":"K0xaYrbcy3"}],"key":"qKzsCOSBAc"},{"type":"listItem","spread":true,"position":{"start":{"line":8,"column":1},"end":{"line":8,"column":1}},"children":[{"type":"paragraph","children":[{"type":"text","value":"Reuse docstrings/comments to generate HTML/PDF without manual copy/paste.","position":{"start":{"line":8,"column":1},"end":{"line":8,"column":1}},"key":"Wumpi4Oimv"}],"key":"XW9XuCqzSi"}],"key":"ONKZvdv0QP"},{"type":"listItem","spread":true,"position":{"start":{"line":9,"column":1},"end":{"line":9,"column":1}},"children":[{"type":"paragraph","children":[{"type":"text","value":"Enforce structure (API vs how-to vs background) so newcomers ramp up fast.","position":{"start":{"line":9,"column":1},"end":{"line":9,"column":1}},"key":"brR5oV8ZB4"}],"key":"mkK8d9dOpV"}],"key":"SJ05ev6zn0"},{"type":"listItem","spread":true,"position":{"start":{"line":10,"column":1},"end":{"line":11,"column":1}},"children":[{"type":"paragraph","children":[{"type":"text","value":"Today: Doxygen for C/C++, Sphinx (MyST) for Python/projects, plus docstring hygiene.","position":{"start":{"line":10,"column":1},"end":{"line":10,"column":1}},"key":"OR65pK1meB"}],"key":"Va40JKOxsg"}],"key":"l4uVj7Jtcl"}],"key":"QoGQve3jUK"},{"type":"thematicBreak","position":{"start":{"line":12,"column":1},"end":{"line":12,"column":1}},"key":"ozFkJ2peEP"},{"type":"heading","depth":2,"position":{"start":{"line":14,"column":1},"end":{"line":14,"column":1}},"children":[{"type":"text","value":"Online resources","position":{"start":{"line":14,"column":1},"end":{"line":14,"column":1}},"key":"fMxAPSlymN"}],"identifier":"online-resources","label":"Online resources","html_id":"online-resources","implicit":true,"key":"zPDFOSa9BC"},{"type":"paragraph","position":{"start":{"line":16,"column":1},"end":{"line":17,"column":1}},"children":[{"type":"text","value":"Doxygen manual:\n","position":{"start":{"line":16,"column":1},"end":{"line":16,"column":1}},"key":"ohJRCn31Ht"},{"type":"link","url":"https://www.doxygen.nl/manual/index.html","position":{"start":{"line":16,"column":1},"end":{"line":16,"column":1}},"children":[{"type":"text","value":"https://​www​.doxygen​.nl​/manual​/index​.html","position":{"start":{"line":16,"column":1},"end":{"line":16,"column":1}},"key":"RVKrUj3wkM"}],"urlSource":"https://www.doxygen.nl/manual/index.html","key":"zfVmyLre44"}],"key":"lixAMA4DKU"},{"type":"paragraph","position":{"start":{"line":19,"column":1},"end":{"line":21,"column":1}},"children":[{"type":"text","value":"Sphinx + MyST:\n","position":{"start":{"line":19,"column":1},"end":{"line":19,"column":1}},"key":"yWJxQa9bDs"},{"type":"link","url":"https://www.sphinx-doc.org/en/master/","position":{"start":{"line":19,"column":1},"end":{"line":19,"column":1}},"children":[{"type":"text","value":"https://​www​.sphinx​-doc​.org​/en​/master/","position":{"start":{"line":19,"column":1},"end":{"line":19,"column":1}},"key":"QkjGsbvcZQ"}],"urlSource":"https://www.sphinx-doc.org/en/master/","key":"Vp8h6KHsvz"},{"type":"break","position":{"start":{"line":19,"column":1},"end":{"line":19,"column":1}},"key":"gRWL6qUrp2"},{"type":"link","url":"https://myst-parser.readthedocs.io/","position":{"start":{"line":19,"column":1},"end":{"line":19,"column":1}},"children":[{"type":"text","value":"https://​myst​-parser​.readthedocs​.io/","position":{"start":{"line":19,"column":1},"end":{"line":19,"column":1}},"key":"mJp24KAVzs"}],"urlSource":"https://myst-parser.readthedocs.io/","key":"koGhLUemf2"}],"key":"BHxbdTDwP9"},{"type":"paragraph","position":{"start":{"line":23,"column":1},"end":{"line":24,"column":1}},"children":[{"type":"text","value":"Autodoc/autosummary:\n","position":{"start":{"line":23,"column":1},"end":{"line":23,"column":1}},"key":"nzpWNgu1SL"},{"type":"link","url":"https://www.sphinx-doc.org/en/master/usage/extensions/autodoc.html","position":{"start":{"line":23,"column":1},"end":{"line":23,"column":1}},"children":[{"type":"text","value":"https://​www​.sphinx​-doc​.org​/en​/master​/usage​/extensions​/autodoc​.html","position":{"start":{"line":23,"column":1},"end":{"line":23,"column":1}},"key":"wiydTRlXL6"}],"urlSource":"https://www.sphinx-doc.org/en/master/usage/extensions/autodoc.html","key":"NAJfMwwZJz"}],"key":"pErnp2KNXr"},{"type":"thematicBreak","position":{"start":{"line":26,"column":1},"end":{"line":26,"column":1}},"key":"zgrwp6oJjs"},{"type":"heading","depth":2,"position":{"start":{"line":28,"column":1},"end":{"line":28,"column":1}},"children":[{"type":"text","value":"Doc types you need","position":{"start":{"line":28,"column":1},"end":{"line":28,"column":1}},"key":"Gvpjrf3iH8"}],"identifier":"doc-types-you-need","label":"Doc types you need","html_id":"doc-types-you-need","implicit":true,"key":"xWA6ExBoR0"},{"type":"table","position":{"start":{"line":30,"column":1},"end":{"line":35,"column":1}},"children":[{"type":"tableRow","position":{"start":{"line":30,"column":1},"end":{"line":30,"column":1}},"children":[{"type":"tableCell","header":true,"position":{"start":{"line":30,"column":1},"end":{"line":30,"column":1}},"children":[{"type":"text","value":"Type","position":{"start":{"line":30,"column":1},"end":{"line":30,"column":1}},"key":"JXH0ysLv8m"}],"key":"c5rX12ozps"},{"type":"tableCell","header":true,"position":{"start":{"line":30,"column":1},"end":{"line":30,"column":1}},"children":[{"type":"text","value":"Purpose","position":{"start":{"line":30,"column":1},"end":{"line":30,"column":1}},"key":"azoivZgYIx"}],"key":"i5HONB9zMx"},{"type":"tableCell","header":true,"position":{"start":{"line":30,"column":1},"end":{"line":30,"column":1}},"children":[{"type":"text","value":"Example","position":{"start":{"line":30,"column":1},"end":{"line":30,"column":1}},"key":"YHPAX3EIL0"}],"key":"LG8TUQu5Ka"}],"key":"DCe7uw4IrU"},{"type":"tableRow","position":{"start":{"line":32,"column":1},"end":{"line":32,"column":1}},"children":[{"type":"tableCell","position":{"start":{"line":32,"column":1},"end":{"line":32,"column":1}},"children":[{"type":"text","value":"Reference","position":{"start":{"line":32,"column":1},"end":{"line":32,"column":1}},"key":"LImw1KYjuZ"}],"key":"Sq280T8hY8"},{"type":"tableCell","position":{"start":{"line":32,"column":1},"end":{"line":32,"column":1}},"children":[{"type":"text","value":"Precise API surface (functions, classes, params).","position":{"start":{"line":32,"column":1},"end":{"line":32,"column":1}},"key":"inx8TB2URO"}],"key":"OEgNwO8zI1"},{"type":"tableCell","position":{"start":{"line":32,"column":1},"end":{"line":32,"column":1}},"children":[{"type":"inlineCode","value":"doxygen","position":{"start":{"line":32,"column":1},"end":{"line":32,"column":1}},"key":"tItzbeaKVP"},{"type":"text","value":" HTML, ","position":{"start":{"line":32,"column":1},"end":{"line":32,"column":1}},"key":"tgBJFJ5zFA"},{"type":"inlineCode","value":"sphinx.ext.autodoc","position":{"start":{"line":32,"column":1},"end":{"line":32,"column":1}},"key":"QQc7oOKpY1"},{"type":"text","value":" pages.","position":{"start":{"line":32,"column":1},"end":{"line":32,"column":1}},"key":"qdxXwf7Mkd"}],"key":"mfHl7YJLwM"}],"key":"VRNZRgYoRo"},{"type":"tableRow","position":{"start":{"line":33,"column":1},"end":{"line":33,"column":1}},"children":[{"type":"tableCell","position":{"start":{"line":33,"column":1},"end":{"line":33,"column":1}},"children":[{"type":"text","value":"How-to","position":{"start":{"line":33,"column":1},"end":{"line":33,"column":1}},"key":"asLtRqFmCP"}],"key":"SqIm4onGlF"},{"type":"tableCell","position":{"start":{"line":33,"column":1},"end":{"line":33,"column":1}},"children":[{"type":"text","value":"Task-focused guides.","position":{"start":{"line":33,"column":1},"end":{"line":33,"column":1}},"key":"dMNRtIb26Z"}],"key":"Z7WdMIRaZB"},{"type":"tableCell","position":{"start":{"line":33,"column":1},"end":{"line":33,"column":1}},"children":[{"type":"text","value":"“Add a new solver”, “Build on GPU”.","position":{"start":{"line":33,"column":1},"end":{"line":33,"column":1}},"key":"r6ksY1PdRb"}],"key":"OXfT3OoNYQ"}],"key":"HZjJHcCgt9"},{"type":"tableRow","position":{"start":{"line":34,"column":1},"end":{"line":34,"column":1}},"children":[{"type":"tableCell","position":{"start":{"line":34,"column":1},"end":{"line":34,"column":1}},"children":[{"type":"text","value":"Tutorials","position":{"start":{"line":34,"column":1},"end":{"line":34,"column":1}},"key":"XelOjO7WIJ"}],"key":"HA6kwJybU5"},{"type":"tableCell","position":{"start":{"line":34,"column":1},"end":{"line":34,"column":1}},"children":[{"type":"text","value":"Narrative, runnable demos.","position":{"start":{"line":34,"column":1},"end":{"line":34,"column":1}},"key":"EHOcwhxzG1"}],"key":"fo5S6SMH3r"},{"type":"tableCell","position":{"start":{"line":34,"column":1},"end":{"line":34,"column":1}},"children":[{"type":"text","value":"Jupyter notebooks or MyST markdown.","position":{"start":{"line":34,"column":1},"end":{"line":34,"column":1}},"key":"vfBsaGL6oe"}],"key":"cWvONBPacN"}],"key":"AJEzZDm4jT"},{"type":"tableRow","position":{"start":{"line":35,"column":1},"end":{"line":35,"column":1}},"children":[{"type":"tableCell","position":{"start":{"line":35,"column":1},"end":{"line":35,"column":1}},"children":[{"type":"text","value":"Explanations","position":{"start":{"line":35,"column":1},"end":{"line":35,"column":1}},"key":"zom7T0MGqL"}],"key":"tLiYYtCju9"},{"type":"tableCell","position":{"start":{"line":35,"column":1},"end":{"line":35,"column":1}},"children":[{"type":"text","value":"Background and design decisions.","position":{"start":{"line":35,"column":1},"end":{"line":35,"column":1}},"key":"JoUc9OGpZG"}],"key":"IIbGzULF5j"},{"type":"tableCell","position":{"start":{"line":35,"column":1},"end":{"line":35,"column":1}},"children":[{"type":"text","value":"“Why we chose PETSc”, “Mesh pipeline”.","position":{"start":{"line":35,"column":1},"end":{"line":35,"column":1}},"key":"mdrMr02MCa"}],"key":"vu5o3D0QFv"}],"key":"RTJBWg9N8U"}],"key":"YzRoGAcZ7A"},{"type":"thematicBreak","position":{"start":{"line":37,"column":1},"end":{"line":37,"column":1}},"key":"fF0pbdtoun"},{"type":"heading","depth":2,"position":{"start":{"line":39,"column":1},"end":{"line":39,"column":1}},"children":[{"type":"text","value":"Doxygen comment syntax","position":{"start":{"line":39,"column":1},"end":{"line":39,"column":1}},"key":"BpovT98w2s"}],"identifier":"doxygen-comment-syntax","label":"Doxygen comment syntax","html_id":"doxygen-comment-syntax","implicit":true,"key":"pAU7pD8omC"},{"type":"list","ordered":false,"spread":false,"position":{"start":{"line":41,"column":1},"end":{"line":45,"column":1}},"children":[{"type":"listItem","spread":true,"position":{"start":{"line":41,"column":1},"end":{"line":41,"column":1}},"children":[{"type":"paragraph","children":[{"type":"inlineCode","value":"/** ... */","position":{"start":{"line":41,"column":1},"end":{"line":41,"column":1}},"key":"l3W9oyix6W"},{"type":"text","value":" or ","position":{"start":{"line":41,"column":1},"end":{"line":41,"column":1}},"key":"SlLer0slmY"},{"type":"inlineCode","value":"///","position":{"start":{"line":41,"column":1},"end":{"line":41,"column":1}},"key":"TzOublM2rG"},{"type":"text","value":" for C/C++; ","position":{"start":{"line":41,"column":1},"end":{"line":41,"column":1}},"key":"E6Udo6DFlF"},{"type":"inlineCode","value":"@brief","position":{"start":{"line":41,"column":1},"end":{"line":41,"column":1}},"key":"maNWxumrLQ"},{"type":"text","value":", ","position":{"start":{"line":41,"column":1},"end":{"line":41,"column":1}},"key":"DRTMKSmqel"},{"type":"inlineCode","value":"@param name","position":{"start":{"line":41,"column":1},"end":{"line":41,"column":1}},"key":"gX8aUxEDlS"},{"type":"text","value":", ","position":{"start":{"line":41,"column":1},"end":{"line":41,"column":1}},"key":"ajXMgdpnLn"},{"type":"inlineCode","value":"@return","position":{"start":{"line":41,"column":1},"end":{"line":41,"column":1}},"key":"LCzhpsbunH"},{"type":"text","value":", ","position":{"start":{"line":41,"column":1},"end":{"line":41,"column":1}},"key":"LpB4uRl0zM"},{"type":"inlineCode","value":"@tparam","position":{"start":{"line":41,"column":1},"end":{"line":41,"column":1}},"key":"QLYxT7CeBa"},{"type":"text","value":".","position":{"start":{"line":41,"column":1},"end":{"line":41,"column":1}},"key":"ONi2ukvKrY"}],"key":"jmGy2MUGFF"}],"key":"IrkHJzfqs3"},{"type":"listItem","spread":true,"position":{"start":{"line":42,"column":1},"end":{"line":42,"column":1}},"children":[{"type":"paragraph","children":[{"type":"text","value":"Use Markdown inside blocks; enable ","position":{"start":{"line":42,"column":1},"end":{"line":42,"column":1}},"key":"ed3fFrGRZ9"},{"type":"inlineCode","value":"MARKDOWN_SUPPORT","position":{"start":{"line":42,"column":1},"end":{"line":42,"column":1}},"key":"CvTj6CsX2m"},{"type":"text","value":".","position":{"start":{"line":42,"column":1},"end":{"line":42,"column":1}},"key":"IcIj9d2qZH"}],"key":"mAppbDQKnO"}],"key":"GlUAYkfQ5F"},{"type":"listItem","spread":true,"position":{"start":{"line":43,"column":1},"end":{"line":43,"column":1}},"children":[{"type":"paragraph","children":[{"type":"text","value":"Group related symbols: ","position":{"start":{"line":43,"column":1},"end":{"line":43,"column":1}},"key":"WqVqsaUs5b"},{"type":"inlineCode","value":"\\addtogroup io","position":{"start":{"line":43,"column":1},"end":{"line":43,"column":1}},"key":"JvWZYmOX2e"},{"type":"text","value":", ","position":{"start":{"line":43,"column":1},"end":{"line":43,"column":1}},"key":"fjW6iMePFI"},{"type":"inlineCode","value":"\\ingroup io","position":{"start":{"line":43,"column":1},"end":{"line":43,"column":1}},"key":"Kjsem7FNUW"},{"type":"text","value":", ","position":{"start":{"line":43,"column":1},"end":{"line":43,"column":1}},"key":"FmqC3mAIf8"},{"type":"inlineCode","value":"\\page","position":{"start":{"line":43,"column":1},"end":{"line":43,"column":1}},"key":"l5ExSouhSk"},{"type":"text","value":", ","position":{"start":{"line":43,"column":1},"end":{"line":43,"column":1}},"key":"vk3KLeg7CA"},{"type":"inlineCode","value":"\\section","position":{"start":{"line":43,"column":1},"end":{"line":43,"column":1}},"key":"BPzL65Kwjq"},{"type":"text","value":".","position":{"start":{"line":43,"column":1},"end":{"line":43,"column":1}},"key":"O7KamN4B3U"}],"key":"XBYyNLZEkO"}],"key":"KoCohBsey4"},{"type":"listItem","spread":true,"position":{"start":{"line":44,"column":1},"end":{"line":45,"column":1}},"children":[{"type":"paragraph","children":[{"type":"text","value":"Prefer documenting headers; keep private symbols hidden unless needed.","position":{"start":{"line":44,"column":1},"end":{"line":44,"column":1}},"key":"p9z40LZ4ON"}],"key":"cHt8FRETtO"}],"key":"JdtAmSvckn"}],"key":"Rcoas5KmYN"},{"type":"thematicBreak","position":{"start":{"line":46,"column":1},"end":{"line":46,"column":1}},"key":"Plfyhcq9qo"},{"type":"heading","depth":2,"position":{"start":{"line":48,"column":1},"end":{"line":48,"column":1}},"children":[{"type":"text","value":"Minimal Doxyfile knobs","position":{"start":{"line":48,"column":1},"end":{"line":48,"column":1}},"key":"nwqybC6RzK"}],"identifier":"minimal-doxyfile-knobs","label":"Minimal Doxyfile knobs","html_id":"minimal-doxyfile-knobs","implicit":true,"key":"NGKwjzlFmn"},{"type":"table","position":{"start":{"line":50,"column":1},"end":{"line":57,"column":1}},"children":[{"type":"tableRow","position":{"start":{"line":50,"column":1},"end":{"line":50,"column":1}},"children":[{"type":"tableCell","header":true,"position":{"start":{"line":50,"column":1},"end":{"line":50,"column":1}},"children":[{"type":"text","value":"Key","position":{"start":{"line":50,"column":1},"end":{"line":50,"column":1}},"key":"HW3qUTO5ir"}],"key":"npp5EugJsA"},{"type":"tableCell","header":true,"position":{"start":{"line":50,"column":1},"end":{"line":50,"column":1}},"children":[{"type":"text","value":"Typical value","position":{"start":{"line":50,"column":1},"end":{"line":50,"column":1}},"key":"oZ4I8EeQWX"}],"key":"OQEZceALiU"},{"type":"tableCell","header":true,"position":{"start":{"line":50,"column":1},"end":{"line":50,"column":1}},"children":[{"type":"text","value":"Why","position":{"start":{"line":50,"column":1},"end":{"line":50,"column":1}},"key":"xH7ZHoHTO5"}],"key":"ZX6kH02zN0"}],"key":"uc0Pgtmj6W"},{"type":"tableRow","position":{"start":{"line":52,"column":1},"end":{"line":52,"column":1}},"children":[{"type":"tableCell","position":{"start":{"line":52,"column":1},"end":{"line":52,"column":1}},"children":[{"type":"inlineCode","value":"PROJECT_NAME","position":{"start":{"line":52,"column":1},"end":{"line":52,"column":1}},"key":"Yxp1fKe6y1"}],"key":"hVm5w1zVw1"},{"type":"tableCell","position":{"start":{"line":52,"column":1},"end":{"line":52,"column":1}},"children":[{"type":"inlineCode","value":"\"MyProject\"","position":{"start":{"line":52,"column":1},"end":{"line":52,"column":1}},"key":"atdUHjoCYe"}],"key":"UEjN3zRjWu"},{"type":"tableCell","position":{"start":{"line":52,"column":1},"end":{"line":52,"column":1}},"children":[{"type":"text","value":"Branding in HTML.","position":{"start":{"line":52,"column":1},"end":{"line":52,"column":1}},"key":"OZOceqXOAO"}],"key":"DWwvx7ttS6"}],"key":"as6IiLogRh"},{"type":"tableRow","position":{"start":{"line":53,"column":1},"end":{"line":53,"column":1}},"children":[{"type":"tableCell","position":{"start":{"line":53,"column":1},"end":{"line":53,"column":1}},"children":[{"type":"inlineCode","value":"INPUT","position":{"start":{"line":53,"column":1},"end":{"line":53,"column":1}},"key":"WlWPZr4W3k"},{"type":"text","value":" / ","position":{"start":{"line":53,"column":1},"end":{"line":53,"column":1}},"key":"UpdH3ErhaM"},{"type":"inlineCode","value":"RECURSIVE","position":{"start":{"line":53,"column":1},"end":{"line":53,"column":1}},"key":"XgnIbpgnCA"}],"key":"wUXTeiNFHm"},{"type":"tableCell","position":{"start":{"line":53,"column":1},"end":{"line":53,"column":1}},"children":[{"type":"inlineCode","value":"src include","position":{"start":{"line":53,"column":1},"end":{"line":53,"column":1}},"key":"EzJYwyGpzS"},{"type":"text","value":" / ","position":{"start":{"line":53,"column":1},"end":{"line":53,"column":1}},"key":"WhjSTDXl8p"},{"type":"inlineCode","value":"YES","position":{"start":{"line":53,"column":1},"end":{"line":53,"column":1}},"key":"nAFOFz5qJ7"}],"key":"pk0hRGmAiM"},{"type":"tableCell","position":{"start":{"line":53,"column":1},"end":{"line":53,"column":1}},"children":[{"type":"text","value":"Where to scan.","position":{"start":{"line":53,"column":1},"end":{"line":53,"column":1}},"key":"ke95OtSslh"}],"key":"FINZItBFwl"}],"key":"QaksNcIGSz"},{"type":"tableRow","position":{"start":{"line":54,"column":1},"end":{"line":54,"column":1}},"children":[{"type":"tableCell","position":{"start":{"line":54,"column":1},"end":{"line":54,"column":1}},"children":[{"type":"inlineCode","value":"FILE_PATTERNS","position":{"start":{"line":54,"column":1},"end":{"line":54,"column":1}},"key":"WyaASzEFMP"}],"key":"YHuJoAU2SG"},{"type":"tableCell","position":{"start":{"line":54,"column":1},"end":{"line":54,"column":1}},"children":[{"type":"inlineCode","value":"*.h *.hpp *.cc *.cpp","position":{"start":{"line":54,"column":1},"end":{"line":54,"column":1}},"key":"tx8kEJLOg5"}],"key":"B0IPCUrSdN"},{"type":"tableCell","position":{"start":{"line":54,"column":1},"end":{"line":54,"column":1}},"children":[{"type":"text","value":"Limit languages.","position":{"start":{"line":54,"column":1},"end":{"line":54,"column":1}},"key":"oz0BsBewmr"}],"key":"S4bmijLyzy"}],"key":"EUiUVJq2vN"},{"type":"tableRow","position":{"start":{"line":55,"column":1},"end":{"line":55,"column":1}},"children":[{"type":"tableCell","position":{"start":{"line":55,"column":1},"end":{"line":55,"column":1}},"children":[{"type":"inlineCode","value":"EXTRACT_ALL","position":{"start":{"line":55,"column":1},"end":{"line":55,"column":1}},"key":"BCE9UL7uqB"}],"key":"stPx6D2cJN"},{"type":"tableCell","position":{"start":{"line":55,"column":1},"end":{"line":55,"column":1}},"children":[{"type":"inlineCode","value":"YES","position":{"start":{"line":55,"column":1},"end":{"line":55,"column":1}},"key":"LTF2hibgnE"},{"type":"text","value":" (for labs)","position":{"start":{"line":55,"column":1},"end":{"line":55,"column":1}},"key":"QvSDle1K2y"}],"key":"ILiYmF5uCy"},{"type":"tableCell","position":{"start":{"line":55,"column":1},"end":{"line":55,"column":1}},"children":[{"type":"text","value":"Show undocumented symbols while learning.","position":{"start":{"line":55,"column":1},"end":{"line":55,"column":1}},"key":"hq2dwWn5tV"}],"key":"NRuIq3CHZt"}],"key":"Wv0d2gzxsU"},{"type":"tableRow","position":{"start":{"line":56,"column":1},"end":{"line":56,"column":1}},"children":[{"type":"tableCell","position":{"start":{"line":56,"column":1},"end":{"line":56,"column":1}},"children":[{"type":"inlineCode","value":"GENERATE_HTML","position":{"start":{"line":56,"column":1},"end":{"line":56,"column":1}},"key":"Rhdb8sk6gS"}],"key":"hxJPF2ZTij"},{"type":"tableCell","position":{"start":{"line":56,"column":1},"end":{"line":56,"column":1}},"children":[{"type":"inlineCode","value":"YES","position":{"start":{"line":56,"column":1},"end":{"line":56,"column":1}},"key":"ZNXMefKYZ5"}],"key":"mnPJVyzowo"},{"type":"tableCell","position":{"start":{"line":56,"column":1},"end":{"line":56,"column":1}},"children":[{"type":"text","value":"Primary output.","position":{"start":{"line":56,"column":1},"end":{"line":56,"column":1}},"key":"nHFWi63oi1"}],"key":"BcKaxUTCjS"}],"key":"eVIv2dvjpk"},{"type":"tableRow","position":{"start":{"line":57,"column":1},"end":{"line":57,"column":1}},"children":[{"type":"tableCell","position":{"start":{"line":57,"column":1},"end":{"line":57,"column":1}},"children":[{"type":"inlineCode","value":"GENERATE_LATEX","position":{"start":{"line":57,"column":1},"end":{"line":57,"column":1}},"key":"OnbYie9i1c"}],"key":"worR7IV746"},{"type":"tableCell","position":{"start":{"line":57,"column":1},"end":{"line":57,"column":1}},"children":[{"type":"inlineCode","value":"NO","position":{"start":{"line":57,"column":1},"end":{"line":57,"column":1}},"key":"ofE3t0QDw1"}],"key":"IPm54YdDmD"},{"type":"tableCell","position":{"start":{"line":57,"column":1},"end":{"line":57,"column":1}},"children":[{"type":"text","value":"Speed up; enable only if PDF needed.","position":{"start":{"line":57,"column":1},"end":{"line":57,"column":1}},"key":"O9EZVw2lih"}],"key":"Nb5k6wQS4Y"}],"key":"pfPzww8Qoo"}],"key":"ZqhGL5LGJp"},{"type":"thematicBreak","position":{"start":{"line":59,"column":1},"end":{"line":59,"column":1}},"key":"ckaFJPVqXc"},{"type":"heading","depth":2,"position":{"start":{"line":61,"column":1},"end":{"line":61,"column":1}},"children":[{"type":"text","value":"Doxygen workflow","position":{"start":{"line":61,"column":1},"end":{"line":61,"column":1}},"key":"uOrHSXLmhi"}],"identifier":"doxygen-workflow","label":"Doxygen workflow","html_id":"doxygen-workflow","implicit":true,"key":"iKj6I1Ajv0"},{"type":"code","lang":"bash","value":"doxygen -g Doxyfile           # create template\nsed -i '' 's/EXTRACT_ALL.*/EXTRACT_ALL = YES/' Doxyfile\ndoxygen Doxyfile              # build HTML in html/ by default","position":{"start":{"line":63,"column":1},"end":{"line":67,"column":1}},"key":"NJ67iygn7Y"},{"type":"list","ordered":false,"spread":false,"position":{"start":{"line":69,"column":1},"end":{"line":72,"column":1}},"children":[{"type":"listItem","spread":true,"position":{"start":{"line":69,"column":1},"end":{"line":69,"column":1}},"children":[{"type":"paragraph","children":[{"type":"text","value":"Open ","position":{"start":{"line":69,"column":1},"end":{"line":69,"column":1}},"key":"vZL2FW2ldS"},{"type":"inlineCode","value":"html/index.html","position":{"start":{"line":69,"column":1},"end":{"line":69,"column":1}},"key":"o2Xl9Yo4pX"},{"type":"text","value":"; fix warnings for undocumented params.","position":{"start":{"line":69,"column":1},"end":{"line":69,"column":1}},"key":"rkYCXsRnbf"}],"key":"yckxOCrF4A"}],"key":"UoGtgf2d4A"},{"type":"listItem","spread":true,"position":{"start":{"line":70,"column":1},"end":{"line":70,"column":1}},"children":[{"type":"paragraph","children":[{"type":"text","value":"Add ","position":{"start":{"line":70,"column":1},"end":{"line":70,"column":1}},"key":"LtVdtNB1BY"},{"type":"inlineCode","value":"docs/doxygen/","position":{"start":{"line":70,"column":1},"end":{"line":70,"column":1}},"key":"jEfWhFc0iK"},{"type":"text","value":" to ","position":{"start":{"line":70,"column":1},"end":{"line":70,"column":1}},"key":"Jah0AnXRkp"},{"type":"inlineCode","value":".gitignore","position":{"start":{"line":70,"column":1},"end":{"line":70,"column":1}},"key":"hBUWP30mlp"},{"type":"text","value":" if you do not publish the artifacts.","position":{"start":{"line":70,"column":1},"end":{"line":70,"column":1}},"key":"anvFye83F5"}],"key":"IuEDaJBu28"}],"key":"PRPhAp2uA2"},{"type":"listItem","spread":true,"position":{"start":{"line":71,"column":1},"end":{"line":72,"column":1}},"children":[{"type":"paragraph","children":[{"type":"text","value":"For mixed C++/Python repos, keep Doxygen focused on C/C++ headers.","position":{"start":{"line":71,"column":1},"end":{"line":71,"column":1}},"key":"lPxBmY1D2H"}],"key":"sc2iwkQ7GF"}],"key":"HoWc5lUaPn"}],"key":"DtyyDStQIq"},{"type":"thematicBreak","position":{"start":{"line":73,"column":1},"end":{"line":73,"column":1}},"key":"FwqJhDNaBq"},{"type":"heading","depth":2,"position":{"start":{"line":75,"column":1},"end":{"line":75,"column":1}},"children":[{"type":"text","value":"Sphinx + MyST quickstart","position":{"start":{"line":75,"column":1},"end":{"line":75,"column":1}},"key":"udmxutehCM"}],"identifier":"sphinx-myst-quickstart","label":"Sphinx + MyST quickstart","html_id":"sphinx-myst-quickstart","implicit":true,"key":"zby8JPqvgc"},{"type":"code","lang":"bash","value":"python -m pip install sphinx myst_parser\nsphinx-quickstart docs","position":{"start":{"line":77,"column":1},"end":{"line":80,"column":1}},"key":"oX4ooF80MM"},{"type":"list","ordered":false,"spread":false,"position":{"start":{"line":82,"column":1},"end":{"line":85,"column":1}},"children":[{"type":"listItem","spread":true,"position":{"start":{"line":82,"column":1},"end":{"line":82,"column":1}},"children":[{"type":"paragraph","children":[{"type":"text","value":"Enable MyST in ","position":{"start":{"line":82,"column":1},"end":{"line":82,"column":1}},"key":"IQaJudVY6m"},{"type":"inlineCode","value":"conf.py","position":{"start":{"line":82,"column":1},"end":{"line":82,"column":1}},"key":"Yj1eDLJurl"},{"type":"text","value":": ","position":{"start":{"line":82,"column":1},"end":{"line":82,"column":1}},"key":"Hl1SNPQY5I"},{"type":"inlineCode","value":"extensions = [\"myst_parser\"]","position":{"start":{"line":82,"column":1},"end":{"line":82,"column":1}},"key":"fTzR0CnadR"},{"type":"text","value":".","position":{"start":{"line":82,"column":1},"end":{"line":82,"column":1}},"key":"qGN8IYqAHa"}],"key":"b93kd0cTr6"}],"key":"ff3Rvmma89"},{"type":"listItem","spread":true,"position":{"start":{"line":83,"column":1},"end":{"line":83,"column":1}},"children":[{"type":"paragraph","children":[{"type":"text","value":"Build: ","position":{"start":{"line":83,"column":1},"end":{"line":83,"column":1}},"key":"trqfXdaiBn"},{"type":"inlineCode","value":"sphinx-build -b html docs docs/_build/html","position":{"start":{"line":83,"column":1},"end":{"line":83,"column":1}},"key":"zh6XpTtjR0"},{"type":"text","value":".","position":{"start":{"line":83,"column":1},"end":{"line":83,"column":1}},"key":"ouRpWjYPfH"}],"key":"g6v5hvQ2XI"}],"key":"EdZWMDCLTK"},{"type":"listItem","spread":true,"position":{"start":{"line":84,"column":1},"end":{"line":85,"column":1}},"children":[{"type":"paragraph","children":[{"type":"text","value":"Keep source in ","position":{"start":{"line":84,"column":1},"end":{"line":84,"column":1}},"key":"UAxsxsvJS5"},{"type":"inlineCode","value":"docs/","position":{"start":{"line":84,"column":1},"end":{"line":84,"column":1}},"key":"rMgz7cku2A"},{"type":"text","value":"; commit ","position":{"start":{"line":84,"column":1},"end":{"line":84,"column":1}},"key":"i3iMSQi6TC"},{"type":"inlineCode","value":"conf.py","position":{"start":{"line":84,"column":1},"end":{"line":84,"column":1}},"key":"ylROFrkwVX"},{"type":"text","value":", ","position":{"start":{"line":84,"column":1},"end":{"line":84,"column":1}},"key":"S58TlBS7n8"},{"type":"inlineCode","value":"index.md","position":{"start":{"line":84,"column":1},"end":{"line":84,"column":1}},"key":"WwTs1gOGmS"},{"type":"text","value":", ","position":{"start":{"line":84,"column":1},"end":{"line":84,"column":1}},"key":"GihA2EluxJ"},{"type":"inlineCode","value":".md","position":{"start":{"line":84,"column":1},"end":{"line":84,"column":1}},"key":"rD0SQpwTTl"},{"type":"text","value":" pages.","position":{"start":{"line":84,"column":1},"end":{"line":84,"column":1}},"key":"hbQ7z2FZSN"}],"key":"JGJvo8BgJw"}],"key":"xWfqQrE2AJ"}],"key":"fUDEWwoG6l"},{"type":"thematicBreak","position":{"start":{"line":86,"column":1},"end":{"line":86,"column":1}},"key":"Vs1HldlvKB"},{"type":"heading","depth":2,"position":{"start":{"line":88,"column":1},"end":{"line":88,"column":1}},"children":[{"type":"text","value":"Sphinx config essentials","position":{"start":{"line":88,"column":1},"end":{"line":88,"column":1}},"key":"Qs1LqZ4O8E"}],"identifier":"sphinx-config-essentials","label":"Sphinx config essentials","html_id":"sphinx-config-essentials","implicit":true,"key":"dI8vApQPDp"},{"type":"table","position":{"start":{"line":90,"column":1},"end":{"line":96,"column":1}},"children":[{"type":"tableRow","position":{"start":{"line":90,"column":1},"end":{"line":90,"column":1}},"children":[{"type":"tableCell","header":true,"position":{"start":{"line":90,"column":1},"end":{"line":90,"column":1}},"children":[{"type":"text","value":"Option","position":{"start":{"line":90,"column":1},"end":{"line":90,"column":1}},"key":"d8hGoG0tVI"}],"key":"C8hBhyIVE7"},{"type":"tableCell","header":true,"position":{"start":{"line":90,"column":1},"end":{"line":90,"column":1}},"children":[{"type":"text","value":"Example","position":{"start":{"line":90,"column":1},"end":{"line":90,"column":1}},"key":"xJZwU6KfaK"}],"key":"m3nekbYzXR"},{"type":"tableCell","header":true,"position":{"start":{"line":90,"column":1},"end":{"line":90,"column":1}},"children":[{"type":"text","value":"Effect","position":{"start":{"line":90,"column":1},"end":{"line":90,"column":1}},"key":"wmIZUayC5K"}],"key":"TAQmenv8lE"}],"key":"Hzo8EndloB"},{"type":"tableRow","position":{"start":{"line":92,"column":1},"end":{"line":92,"column":1}},"children":[{"type":"tableCell","position":{"start":{"line":92,"column":1},"end":{"line":92,"column":1}},"children":[{"type":"inlineCode","value":"extensions","position":{"start":{"line":92,"column":1},"end":{"line":92,"column":1}},"key":"AvWXgI2sLL"}],"key":"zKheMrwmu7"},{"type":"tableCell","position":{"start":{"line":92,"column":1},"end":{"line":92,"column":1}},"children":[{"type":"inlineCode","value":"[\"myst_parser\", \"sphinx.ext.autodoc\", \"sphinx.ext.autosummary\", \"sphinx.ext.napoleon\"]","position":{"start":{"line":92,"column":1},"end":{"line":92,"column":1}},"key":"lLPaCODXzh"}],"key":"A1qZd1QkxE"},{"type":"tableCell","position":{"start":{"line":92,"column":1},"end":{"line":92,"column":1}},"children":[{"type":"text","value":"Enable markdown, API import, summary tables, Google/NumPy docstrings.","position":{"start":{"line":92,"column":1},"end":{"line":92,"column":1}},"key":"Px12NgHh2w"}],"key":"DmWCF9cHvS"}],"key":"WzrGbDiiOR"},{"type":"tableRow","position":{"start":{"line":93,"column":1},"end":{"line":93,"column":1}},"children":[{"type":"tableCell","position":{"start":{"line":93,"column":1},"end":{"line":93,"column":1}},"children":[{"type":"inlineCode","value":"autosummary_generate","position":{"start":{"line":93,"column":1},"end":{"line":93,"column":1}},"key":"qKVoELfFgL"}],"key":"pzP5FDYhDN"},{"type":"tableCell","position":{"start":{"line":93,"column":1},"end":{"line":93,"column":1}},"children":[{"type":"inlineCode","value":"True","position":{"start":{"line":93,"column":1},"end":{"line":93,"column":1}},"key":"KakZkNOMn6"}],"key":"iwhpogbE2v"},{"type":"tableCell","position":{"start":{"line":93,"column":1},"end":{"line":93,"column":1}},"children":[{"type":"text","value":"Auto-create stub pages for modules/classes.","position":{"start":{"line":93,"column":1},"end":{"line":93,"column":1}},"key":"oX7W4O7fas"}],"key":"AToXBNtY2B"}],"key":"pl29MZC2fB"},{"type":"tableRow","position":{"start":{"line":94,"column":1},"end":{"line":94,"column":1}},"children":[{"type":"tableCell","position":{"start":{"line":94,"column":1},"end":{"line":94,"column":1}},"children":[{"type":"inlineCode","value":"html_theme","position":{"start":{"line":94,"column":1},"end":{"line":94,"column":1}},"key":"FQ5e5DoFMx"}],"key":"xmxM5A2Mba"},{"type":"tableCell","position":{"start":{"line":94,"column":1},"end":{"line":94,"column":1}},"children":[{"type":"inlineCode","value":"\"furo\"","position":{"start":{"line":94,"column":1},"end":{"line":94,"column":1}},"key":"iN5DpxIFfB"},{"type":"text","value":" or ","position":{"start":{"line":94,"column":1},"end":{"line":94,"column":1}},"key":"DCllS5AVAB"},{"type":"inlineCode","value":"\"sphinx_rtd_theme\"","position":{"start":{"line":94,"column":1},"end":{"line":94,"column":1}},"key":"rmhvKRBrjh"}],"key":"Yjna8iW5X2"},{"type":"tableCell","position":{"start":{"line":94,"column":1},"end":{"line":94,"column":1}},"children":[{"type":"text","value":"Choose a clean default theme.","position":{"start":{"line":94,"column":1},"end":{"line":94,"column":1}},"key":"xcvoyYg2S3"}],"key":"oWdJOxQX3z"}],"key":"d5HsiP2C0e"},{"type":"tableRow","position":{"start":{"line":95,"column":1},"end":{"line":95,"column":1}},"children":[{"type":"tableCell","position":{"start":{"line":95,"column":1},"end":{"line":95,"column":1}},"children":[{"type":"inlineCode","value":"templates_path","position":{"start":{"line":95,"column":1},"end":{"line":95,"column":1}},"key":"LGoD09tGV6"},{"type":"text","value":" / ","position":{"start":{"line":95,"column":1},"end":{"line":95,"column":1}},"key":"DCo9vmV27P"},{"type":"inlineCode","value":"exclude_patterns","position":{"start":{"line":95,"column":1},"end":{"line":95,"column":1}},"key":"W39oiiM0Mt"}],"key":"GLDHJEGz4k"},{"type":"tableCell","position":{"start":{"line":95,"column":1},"end":{"line":95,"column":1}},"children":[{"type":"inlineCode","value":"[\"_templates\"]","position":{"start":{"line":95,"column":1},"end":{"line":95,"column":1}},"key":"JocDGbErTN"},{"type":"text","value":" / ","position":{"start":{"line":95,"column":1},"end":{"line":95,"column":1}},"key":"Xu3gv32cBd"},{"type":"inlineCode","value":"[\"_build\"]","position":{"start":{"line":95,"column":1},"end":{"line":95,"column":1}},"key":"IfJOPVjjet"}],"key":"PcTEyHiLw3"},{"type":"tableCell","position":{"start":{"line":95,"column":1},"end":{"line":95,"column":1}},"children":[{"type":"text","value":"Keep builds out of the tree.","position":{"start":{"line":95,"column":1},"end":{"line":95,"column":1}},"key":"VlxmgtFLYz"}],"key":"H5Gqugvw1z"}],"key":"rwzQnPhbR0"},{"type":"tableRow","position":{"start":{"line":96,"column":1},"end":{"line":96,"column":1}},"children":[{"type":"tableCell","position":{"start":{"line":96,"column":1},"end":{"line":96,"column":1}},"children":[{"type":"inlineCode","value":"nitpicky","position":{"start":{"line":96,"column":1},"end":{"line":96,"column":1}},"key":"g6BNxNQ4uF"}],"key":"J4Egs6gSJX"},{"type":"tableCell","position":{"start":{"line":96,"column":1},"end":{"line":96,"column":1}},"children":[{"type":"inlineCode","value":"True","position":{"start":{"line":96,"column":1},"end":{"line":96,"column":1}},"key":"LNirM266ul"}],"key":"qEat4ns5xv"},{"type":"tableCell","position":{"start":{"line":96,"column":1},"end":{"line":96,"column":1}},"children":[{"type":"text","value":"Fail on broken references; keeps links healthy.","position":{"start":{"line":96,"column":1},"end":{"line":96,"column":1}},"key":"u4PP9844Tf"}],"key":"QkBKs3AnUo"}],"key":"eRzKZJUowb"}],"key":"OP0kphvucT"},{"type":"thematicBreak","position":{"start":{"line":98,"column":1},"end":{"line":98,"column":1}},"key":"OB6oCkSMUt"},{"type":"heading","depth":2,"position":{"start":{"line":100,"column":1},"end":{"line":100,"column":1}},"children":[{"type":"text","value":"Docstring styles (Python)","position":{"start":{"line":100,"column":1},"end":{"line":100,"column":1}},"key":"cXigcW5JBQ"}],"identifier":"docstring-styles-python","label":"Docstring styles (Python)","html_id":"docstring-styles-python","implicit":true,"key":"cOvBIQwopl"},{"type":"code","lang":"python","value":"def step(x, *, atol=1e-8):\n    \"\"\"Compute a damped step.\n\n    Args:\n        x (float): Current iterate.\n        atol (float, optional): Absolute tolerance.\n\n    Returns:\n        float: Next iterate.\n    \"\"\"","position":{"start":{"line":102,"column":1},"end":{"line":113,"column":1}},"key":"qYCuuqzQZq"},{"type":"list","ordered":false,"spread":false,"position":{"start":{"line":115,"column":1},"end":{"line":118,"column":1}},"children":[{"type":"listItem","spread":true,"position":{"start":{"line":115,"column":1},"end":{"line":115,"column":1}},"children":[{"type":"paragraph","children":[{"type":"text","value":"Google/NumPy/NumpyDoc formats all work with ","position":{"start":{"line":115,"column":1},"end":{"line":115,"column":1}},"key":"kyUBlewu64"},{"type":"inlineCode","value":"sphinx.ext.napoleon","position":{"start":{"line":115,"column":1},"end":{"line":115,"column":1}},"key":"t0eEOX9j5G"},{"type":"text","value":".","position":{"start":{"line":115,"column":1},"end":{"line":115,"column":1}},"key":"BfH1tZAyfw"}],"key":"wGpBDqRavD"}],"key":"iP6pJrfLGw"},{"type":"listItem","spread":true,"position":{"start":{"line":116,"column":1},"end":{"line":116,"column":1}},"children":[{"type":"paragraph","children":[{"type":"text","value":"Keep one-line summary on top; include types and units where relevant.","position":{"start":{"line":116,"column":1},"end":{"line":116,"column":1}},"key":"mQxMv70vDV"}],"key":"YFkJHpNFJc"}],"key":"G4NZdLXxu7"},{"type":"listItem","spread":true,"position":{"start":{"line":117,"column":1},"end":{"line":118,"column":1}},"children":[{"type":"paragraph","children":[{"type":"text","value":"Show examples in doctests to validate docs automatically.","position":{"start":{"line":117,"column":1},"end":{"line":117,"column":1}},"key":"gfLNEItdgz"}],"key":"iqjsKrbJCy"}],"key":"rd8dyEz6vW"}],"key":"UPtMTegI0Y"},{"type":"thematicBreak","position":{"start":{"line":119,"column":1},"end":{"line":119,"column":1}},"key":"jlbJNOFaYs"},{"type":"heading","depth":2,"position":{"start":{"line":121,"column":1},"end":{"line":121,"column":1}},"children":[{"type":"text","value":"Autodoc + autosummary pages","position":{"start":{"line":121,"column":1},"end":{"line":121,"column":1}},"key":"oB4X5D1kdt"}],"identifier":"autodoc-autosummary-pages","label":"Autodoc + autosummary pages","html_id":"autodoc-autosummary-pages","implicit":true,"key":"J2M3wYLATT"},{"type":"code","lang":"md","value":"```{autosummary}\n:toctree: api\n:recursive:\nmyproj.module\nmyproj.module.Class","position":{"start":{"line":123,"column":1},"end":{"line":129,"column":1}},"key":"icBEqMC1rk"},{"type":"code","lang":"","value":"\n- Imports modules during the build—ensure dependencies are installed or mock them via `autodoc_mock_imports`.\n- Combine with MyST prose pages so API links appear inline (`{py:func}` roles).\n- Regenerate stubs after adding modules; commit the generated `.rst`/`.md` files.\n\n----\n\n## Connecting C++ and Sphinx\n\n- To present C++ APIs alongside Python docs, export XML from Doxygen (`GENERATE_XML=YES`) and bridge via `breathe`.\n- Use `.. doxygenfunction::` / `.. doxygenclass::` directives inside MyST (````{eval-rst}``` blocks).\n- Keep namespaces short and header paths consistent to avoid duplicate entries.\n\n----\n\n## Publishing docs\n\n- Local preview: `python -m http.server 8000 -d docs/_build/html`.\n- CI/Pages: build with `sphinx-build -b html ...` then upload `_build/html` to GitHub Pages/Artifacts.\n- Cache virtualenvs and Doxygen output in CI to speed builds; fail the job on warnings.\n- Add `docs/` target to `Makefile` for one-liners (`make docs-html`, `make doxygen`).\n\n----\n\n## Lab 05 outline\n\n- Copy the provided VWCE C++/Python examples into `./<name.surname>/` in your `sspa-sandbox` clone.\n- Add Doxygen comments/docstrings, generate HTML+XML with `doxygen` in the `sspa/docs` container, and fix warnings.\n- Build Sphinx+MyST with `autodoc`, `autosummary`, `napoleon`, and `breathe` to combine Python API and C++ XML.\n- Add a short tutorial page and verify cross-links (`sphinx-build -n`), then push a branch and open a PR to the teachers’ repo.","position":{"start":{"line":131,"column":1},"end":{"line":161,"column":1}},"key":"TD4xkNMhXG"}],"key":"q72L4xT8n5"}],"key":"jWzq2UCjgk"},"references":{"cite":{"order":[],"data":{}}},"footer":{"navigation":{"prev":{"title":"Collaborative Git Workflows","url":"/slides/slides04","group":"Slides content"},"next":{"title":"Unit and Functional Testing","url":"/slides/slides06","group":"Slides content"}}},"domain":"http://localhost:3000"}